<?xml version="1.0" encoding="UTF-8"?>
<!--
  ~ [y] hybris Platform
  ~
  ~ Copyright (c) 2000-2015 hybris AG
  ~ All rights reserved.
  ~
  ~ This software is the confidential and proprietary information of hybris
  ~ ("Confidential Information"). You shall not disclose such Confidential
  ~ Information and shall use it only in accordance with the terms of the
  ~ license agreement you entered into with hybris.
  -->

<editor>
	<group qualifier="General" visible="true" initially-opened="true">
		<label key="cockpit.config.label.General" />
		<property qualifier="commentattachment.item">
			<parameter>
				<name>allowCreate</name>
				<value>true</value>
			</parameter>
			<parameter>
				<name>allowAutocompletion</name>
				<value>true</value>
			</parameter>
			<parameter>
				<name>autocompletionSearchType</name>
				<value>Media</value>
			</parameter>
			<parameter>
				<name>restrictToCreateTypes</name>
				<value>Product+,Category+,Media,CelumAsset+,MediaContainer+,PriceRow+,Principal+,Voucher+,Promotion+</value>
			</parameter>
		</property>
		<property qualifier="commentattachment.abstractComment" />
	</group>
</editor>
